{
	"itemGroup.quartzchests": "石英箱",
	"block.quartzchests.chest": "石英箱",
	"block.quartzchests.chest.label": "標籤",
	"block.quartzchests.chest.label.unnamed": "未命名",
	"block.quartzchests.chest.chest_color": "箱子顏色",
	"block.quartzchests.chest.border_color": "邊框顏色",
	"block.quartzchests.chest.text_color": "文字顏色",
	"block.quartzchests.chest.icon": "標誌",
	"block.quartzchests.chest.slots_used": "已使用 %d/%d 格插槽",
	"block.quartzchests.chest.upgrades": "升級:",
	"item.quartzchests.upgrade": "石英箱升級",
	"item.quartzchests.keep_inventory_upgrade": "保留庫存升級",
	"item.quartzchests.glowing_text_upgrade": "發光文字升級",
	"item.quartzchests.bold_text_upgrade": "粗體文字升級",
	"item.quartzchests.italic_text_upgrade": "斜體文字升級"
}
